tabcorr/__init__.py
tabcorr/aa_cosmos.txt
tabcorr/aa_test_cosmos.txt
tabcorr/as_cosmos.csv
tabcorr/corrfunc.py
tabcorr/database.py
tabcorr/interpolator.py
tabcorr/tabcorr.py
tabcorr-1.2.1.dist-info/licenses/LICENSE
tabcorr-1.2.1.dist-info/WHEEL
tabcorr-1.2.1.dist-info/METADATA
tabcorr-1.2.1.dist-info/RECORD
