Metadata-Version: 2.4
Name: tabcorr
Version: 1.2.1
Summary: Tabulated Correlation Functions
Author-email: "Johannes U. Lange" <jlange@american.edu>
License-Expression: MIT
License-File: LICENSE
Requires-Dist: numpy
Requires-Dist: scipy
Requires-Dist: astropy>=7.0
Requires-Dist: h5py
Requires-Dist: tqdm
Requires-Dist: halotools
Project-URL: Home, https://tabcorr.readthedocs.io
